ifhir/__init__.py
ifhir/ifhir.py
ifhir-0.2.data/scripts/ifhir.py
ifhir-0.2.dist-info/licenses/LICENSE
ifhir-0.2.dist-info/METADATA
ifhir-0.2.dist-info/WHEEL
ifhir-0.2.dist-info/top_level.txt
ifhir-0.2.dist-info/RECORD
